{
	"credit": "Made with Blockbench",
	"textures": {
		"1": "model_textures/podcast/music_1",
		"particle": "model_textures/podcast/music_2",
		"b": "model_textures/podcast/music_2"
	},
	"elements": [
		{
			"from": [0.9, -12.1, 5.65],
			"to": [15.1, -1.9, 7.85],
			"rotation": {"angle": 0, "axis": "y", "origin": [16, -3, 14]},
			"faces": {
				"north": {"uv": [12.75, 4, 14.5, 5.25], "texture": "#b", "tintindex": 0},
				"east": {"uv": [12.75, 4, 12.875, 5.25], "texture": "#b", "tintindex": 0},
				"south": {"uv": [11.875, 7, 13.625, 8.25], "texture": "#b", "tintindex": 0},
				"west": {"uv": [12.75, 4, 12.875, 5.25], "texture": "#b", "tintindex": 0},
				"up": {"uv": [15.75, 5.5, 14, 5.75], "texture": "#b", "tintindex": 0},
				"down": {"uv": [14.375, 5.125, 14.25, 5.25], "rotation": 180, "texture": "#b", "tintindex": 0}
			}
		},
		{
			"from": [0, -13, 6.75],
			"to": [16, 10, 6.75],
			"rotation": {"angle": 0, "axis": "y", "origin": [16, -4, 13.75]},
			"faces": {
				"north": {"uv": [12.75, 0, 14.75, 2.875], "texture": "#b", "tintindex": 0},
				"south": {"uv": [13.75, 5.5, 11.75, 8.375], "texture": "#b", "tintindex": 0}
			}
		},
		{
			"from": [0, -13, 6.75],
			"to": [16, 10, 6.75],
			"rotation": {"angle": 0, "axis": "y", "origin": [16, -4, 13.75]},
			"faces": {
				"north": {"uv": [12.75, 0, 14.75, 2.875], "texture": "#1"},
				"south": {"uv": [14.75, 0, 12.75, 2.875], "texture": "#1"}
			}
		},
		{
			"from": [1, -5, 5.75],
			"to": [14, 4, 7.75],
			"rotation": {"angle": 22.5, "axis": "z", "origin": [7.5, -0.5, 6.5]},
			"faces": {
				"north": {"uv": [12.875, 2.875, 14.5, 4], "texture": "#b", "tintindex": 0},
				"east": {"uv": [14.75, 4, 14.5, 5.125], "texture": "#b", "tintindex": 0},
				"south": {"uv": [13.25, 8.375, 11.625, 9.5], "texture": "#b", "tintindex": 0},
				"west": {"uv": [14.5, 4.125, 14.75, 5.25], "texture": "#b", "tintindex": 0},
				"up": {"uv": [12.75, 5.25, 14.375, 5.5], "texture": "#b", "tintindex": 0},
				"down": {"uv": [14.5, 3.875, 12.875, 4], "texture": "#b", "tintindex": 0}
			}
		},
		{
			"from": [0.99, -5.01, 5.74],
			"to": [14.01, 4.01, 7.76],
			"rotation": {"angle": 22.5, "axis": "z", "origin": [7.5, -0.5, 6.5]},
			"faces": {
				"north": {"uv": [12.875, 2.875, 14.5, 4], "texture": "#1"},
				"east": {"uv": [14.75, 4, 14.5, 5.25], "texture": "#1"},
				"south": {"uv": [13.25, 8.375, 11.625, 9.5], "texture": "#1"},
				"west": {"uv": [14.5, 4.125, 14.75, 5.25], "texture": "#1"},
				"up": {"uv": [12.75, 5.25, 14.375, 5.5], "texture": "#1"},
				"down": {"uv": [14.5, 3.875, 12.875, 4], "texture": "#1"}
			}
		},
		{
			"from": [0.89, -12.11, 5.64],
			"to": [15.11, -1.89, 7.86],
			"rotation": {"angle": 0, "axis": "y", "origin": [16, -3, 14]},
			"faces": {
				"north": {"uv": [12.75, 4, 14.5, 5.25], "texture": "#1"},
				"east": {"uv": [14.75, 4.125, 14.5, 5.25], "texture": "#1"},
				"south": {"uv": [11.875, 7, 13.625, 8.25], "texture": "#1"},
				"west": {"uv": [14.5, 4.125, 14.75, 5.25], "texture": "#1"},
				"up": {"uv": [15.75, 5.5, 14, 5.75], "texture": "#1"},
				"down": {"uv": [14.75, 4, 14.5, 5.25], "rotation": 90, "texture": "#1"}
			}
		},
		{
			"from": [6, 3, 6],
			"to": [10, 21, 7],
			"rotation": {"angle": 0, "axis": "y", "origin": [14, 14, 8]},
			"faces": {
				"north": {"uv": [12.25, 3, 12.75, 5.25], "texture": "#b"},
				"east": {"uv": [14.75, 3, 14.875, 5.25], "texture": "#b"},
				"south": {"uv": [15.25, 3, 14.75, 5.25], "texture": "#b"},
				"west": {"uv": [15.125, 3, 15.25, 5.25], "texture": "#b"},
				"up": {"uv": [12.75, 3, 12.25, 3.125], "texture": "#b"},
				"down": {"uv": [12.75, 3, 12.25, 3.125], "texture": "#b"}
			}
		},
		{
			"from": [6, -7, 5.5],
			"to": [10, 27, 5.5],
			"rotation": {"angle": 0, "axis": "y", "origin": [14, 14, 8]},
			"faces": {
				"north": {"uv": [11.375, 1.75, 12.25, 5.25], "texture": "#b"},
				"south": {"uv": [12.25, 1.75, 11.375, 5.25], "texture": "#b"}
			}
		},
		{
			"from": [5.9, 19.9, 5.9],
			"to": [10.1, 29.1, 7.1],
			"rotation": {"angle": 22.5, "axis": "z", "origin": [8, 23, 6.5]},
			"faces": {
				"north": {"uv": [12.25, 1.875, 12.75, 3], "texture": "#b"},
				"east": {"uv": [12.25, 1.875, 12.375, 3], "texture": "#b"},
				"south": {"uv": [15.75, 4.125, 15.25, 5.25], "texture": "#b"},
				"west": {"uv": [12.625, 1.875, 12.75, 3], "texture": "#b"},
				"up": {"uv": [14.75, 3.125, 14.875, 3.5], "texture": "#b"},
				"down": {"uv": [15.125, 3.125, 15.25, 3.5], "texture": "#b"}
			}
		},
		{
			"from": [4, 19, 6.5],
			"to": [12, 29, 6.5],
			"rotation": {"angle": 22.5, "axis": "z", "origin": [8, 23, 6]},
			"faces": {
				"north": {"uv": [11.625, 0.5, 12.625, 1.75], "texture": "#b"},
				"south": {"uv": [12.625, 0.5, 11.625, 1.75], "texture": "#b"}
			}
		}
	],
	"gui_light": "front",
	"display": {
		"thirdperson_righthand": {
			"rotation": [70.29, -3.05, 88.83],
			"translation": [-7.5, -4, 1.25],
			"scale": [0.66, 0.66, 0.66]
		},
		"thirdperson_lefthand": {
			"rotation": [84, 34, -33.25],
			"translation": [1, 1.25, 2.75],
			"scale": [0.3125, 0.3125, 0.3125]
		},
		"firstperson_righthand": {
			"rotation": [3, 112, -13],
			"translation": [9.5, 2, -5.75],
			"scale": [0.33398, 0.33398, 0.33398]
		},
		"firstperson_lefthand": {
			"rotation": [3, 112, -13],
			"translation": [9.5, 2, -5.75],
			"scale": [0.33398, 0.33398, 0.33398]
		},
		"ground": {
			"translation": [0, 5.5, 0],
			"scale": [0.29101, 0.29101, 0.29101]
		},
		"gui": {
			"rotation": [5, -165.75, -1.75],
			"scale": [0.33359, 0.33359, 0.33359]
		},
		"head": {
			"rotation": [10, 0, 0],
			"translation": [0, -19.25, 0],
			"scale": [1.2, 1.2, 1.2]
		}
	}
}